{
    "Advance (GBA)": "Advance (GBA)",
    "Atari 2600 (A2600)": "Atari 2600 (A2600)",
    "Atari 7800 (A7800)": "Atari 7800 (A7800)",
    "Bandai": "Bandai",
    "Color (GBC)": "Color (GBC)",
    "Commodore 128 (C128)": "Commodore 128 (C128)",
    "Commodore 64 (C64)": "Commodore 64 (C64)",
    "Commodore 64 Direct-to-TV (C64)": "Commodore 64 Direct-to-TV (C64)",
    "Commodore CBM-II (CBM-II)": "Commodore CBM-II (CBM-II)",
    "Commodore PET (PET)": "Commodore PET (PET)",
    "Commodore PLUS4 (PLUS4)": "Commodore PLUS4 (PLUS4)",
    "Commodore VIC20 (VIC20)": "Commodore VIC20 (VIC20)",
    "Game Boy (GB)": "Game Boy (GB)",
    "Game Boy Advance (GBA)": "Game Boy Advance (GBA)",
    "Game Boy Color (GBC)": "Game Boy Color (GBC)",
    "Multiplatform": "Multiplatform",
    "NEC": "NEC",
    "Nintendo (NES)": "Nintendo (NES)",
    "Nintendo 3DS (3DS)": "Nintendo 3DS (3DS)",
    "Nintendo 64 (N64)": "Nintendo 64 (N64)",
    "Nintendo DS (NDS)": "Nintendo DS (NDS)",
    "Nintendo Game Boy (GB)": "Nintendo Game Boy (GB)",
    "Nintendo GameCube (GC)": "Nintendo GameCube (GC)",
    "Nintendo Virtual Boy (VB)": "Nintendo Virtual Boy (VB)",
    "Nintendo Wii (Wii)": "Nintendo Wii (Wii)",
    "Nintendo Wii U (Wii U)": "Nintendo Wii U (Wii U)",
    "SNK": "SNK",
    "Sega": "Sega",
    "Sega 32X (32X)": "Sega 32X (32X)",
    "Sega Dreamcast (DC)": "Sega Dreamcast (DC)",
    "Sega Mega Drive (SMD)": "Sega Mega Drive (SMD)",
    "Sony": "Sony",
    "Sony PlayStation (PSX)": "Sony PlayStation (PSX)",
    "Sony PlayStation 2 (PS2)": "Sony PlayStation 2 (PS2)",
    "Sony PlayStation 3 (PS3)": "Sony PlayStation 3 (PS3)",
    "Sony PlayStation Portable (PSP)": "Sony PlayStation Portable (PSP)"
}